LICENSE
README.md
setup.cfg
setup.py
smc3/__init__.py
smc3/box.py
smc3/loggable.py
smc3/motor.py
smc3/protocol.py
smc3.egg-info/PKG-INFO
smc3.egg-info/SOURCES.txt
smc3.egg-info/dependency_links.txt
smc3.egg-info/requires.txt
smc3.egg-info/top_level.txt