Metadata-Version: 2.1
Name: smc3
Version: 0.1.1
Summary: Simulation Motor Controller interface
Home-page: https://github.com/zmij/pysmc3
Download-URL: https://github.com/zmij/pysmc3/archive/refs/tags/v0.1.tar.gz
Author: Sergei A. Fedorov
Author-email: sergei.a.fedorov@gmail.com
License: Apache-2.0
Keywords: motion simulation,motor control,diagnostic tools
Classifier: Development Status :: 3 - Alpha
Classifier: Intended Audience :: Developers
Classifier: Topic :: Games/Entertainment :: Simulation
Classifier: Operating System :: POSIX :: Linux
Classifier: Operating System :: MacOS
Classifier: License :: OSI Approved :: Apache Software License
Classifier: Programming Language :: Python :: 3
Classifier: Programming Language :: Python :: 3.4
Classifier: Programming Language :: Python :: 3.5
Classifier: Programming Language :: Python :: 3.6
License-File: LICENSE
